al1s/drivers/kali/__init__.py
al1s/drivers/kali/driver.py
test/__init__.py
test/main.py
kali_driver-0.0.0.dist-info/METADATA
kali_driver-0.0.0.dist-info/WHEEL
kali_driver-0.0.0.dist-info/top_level.txt
kali_driver-0.0.0.dist-info/RECORD
